Metadata-Version: 1.0
Name: botany-noughtsandcrosses
Version: 0.1.0
Summary: Botany noughtsandcrosses
Home-page: http://github.com/inglesp/botany
Author: Peter Inglesby
Author-email: peter.inglesby@gmail.com
License: License :: OSI Approved :: MIT License
Platform: UNKNOWN
